README.md
setup.py
rancidtoolkit2/__init__.py
rancidtoolkit2/cisco.py
rancidtoolkit2/juniper.py
rancidtoolkit2/oxidized.py
rancidtoolkit2/rancid.py
rancidtoolkit2/rtconfig.py
rancidtoolkit2.egg-info/PKG-INFO
rancidtoolkit2.egg-info/SOURCES.txt
rancidtoolkit2.egg-info/dependency_links.txt
rancidtoolkit2.egg-info/not-zip-safe
rancidtoolkit2.egg-info/requires.txt
rancidtoolkit2.egg-info/top_level.txt