Metadata-Version: 1.1
Name: rancidtoolkit2
Version: 0.2
Summary: Functions to parse network devices config files and output specific data
Home-page: UNKNOWN
Author: Marcus Stoegbauer
Author-email: lysis@lys.is
License: MIT
Platform: UNKNOWN
Classifier: Development Status :: 4 - Beta
Classifier: Intended Audience :: Developers
Classifier: License :: OSI Approved :: MIT License
Classifier: Programming Language :: Python
